renpyfmt/__init__.py
renpyfmt/cli.py
renpyfmt/code_format.py
renpyfmt/common.py
renpyfmt-1.0.0.dist-info/METADATA
renpyfmt-1.0.0.dist-info/entry_points.txt
renpyfmt-1.0.0.dist-info/WHEEL
renpyfmt-1.0.0.dist-info/LICENSE
renpyfmt-1.0.0.dist-info/RECORD
