Metadata-Version: 2.1
Name: renpyfmt
Version: 1.0.0
Summary: A Ren'Py formatter.
License: MIT
Author: cobaltcore
Author-email: cobaltcore@yandex.com
Requires-Python: >=3.10,<3.12
Classifier: License :: OSI Approved :: MIT License
Classifier: Programming Language :: Python :: 3
Classifier: Programming Language :: Python :: 3.10
Classifier: Programming Language :: Python :: 3.11
Requires-Dist: mypy-extensions (>=0.4.3,<0.5.0)
Requires-Dist: pathspec (>=0.11.0,<0.12.0)
Requires-Dist: rich-click (>=1.6.1,<2.0.0)
